{
  "project_info": {
    "project_number": "544512404805",
    "firebase_url": "https://g1expertrules.firebaseio.com",
    "project_id": "g1expertrules",
    "storage_bucket": "g1expertrules.appspot.com"
  },
  "client": [
    {
      "client_info": {
        "mobilesdk_app_id": "1:544512404805:android:9203b3a139aa42e6dd622c",
        "android_client_info": {
          "package_name": "com.example.teamorange_capstone_android"
        }
      },
      "oauth_client": [
        {
          "client_id": "544512404805-t5b44d6o1gdofgrm36bepk583fq2bdqd.apps.googleusercontent.com",
          "client_type": 3
        }
      ],
      "api_key": [
        {
          "current_key": "AIzaSyAgmoqx3QCG7Q8DXrvaPUUdzmBsATKa6Uk"
        }
      ],
      "services": {
        "appinvite_service": {
          "other_platform_oauth_client": [
            {
              "client_id": "544512404805-t5b44d6o1gdofgrm36bepk583fq2bdqd.apps.googleusercontent.com",
              "client_type": 3
            }
          ]
        }
      }
    }
  ],
  "configuration_version": "1"
}